app/__init__.py
app/api/__init__.py
app/api/app_api.py
app/api/auth_api.py
app/api/databases_api.py
app/api/datafiles_api.py
app/api/macrofiles_api.py
app/api/scripts_api.py
app/api/ui.py
app/api/users_api.py
app/app.py
app/auth/__init__.py
app/auth/jwt_auth.py
app/auth/oauth.py
app/cli/__init__.py
app/cli/app_cmd.py
app/cli/init_cmd.py
app/cli/users_cmd.py
app/constants.py
app/errors/__inti__.py
app/errors/errors.py
app/lib/__init__.py
app/lib/database/__index__.py
app/lib/database/connection.py
app/lib/database/registry.py
app/lib/database/validation.py
app/lib/fs.py
app/lib/users.py
app/logging.py
app/macros/index.py
app/macros/macros.py
app/migrations/README
app/migrations/alembic.ini
app/migrations/env.py
app/migrations/script.py.mako
app/migrations/versions/5efb9dfe7458_init.py
app/models/__init__.py
app/models/base.py
app/models/database.py
app/models/datafile.py
app/models/macrofile.py
app/models/mixins/user_space_mixin.py
app/models/script.py
app/models/user.py
app/schemas/__init__.py
app/schemas/app_schema.py
app/schemas/auth_schema.py
app/schemas/base.py
app/schemas/database_schema.py
app/schemas/datafile_schema.py
app/schemas/macrofile_schema.py
app/schemas/script_schema.py
app/schemas/user_schema.py
app/settings.py
app/static/app.svg
app/static/assets/index-2hmaE3TP.js
app/static/assets/index-3Xxu9hY7.js
app/static/assets/index-4XlKubOb.js
app/static/assets/index-4cqGH0if.js
app/static/assets/index-A3491VH_.js
app/static/assets/index-B6jj9dtV.js
app/static/assets/index-B8MQB6zc.js
app/static/assets/index-B8dnVPCS.css
app/static/assets/index-BA4sb7KR.js
app/static/assets/index-BAjLin9s.js
app/static/assets/index-BKCpts3W.js
app/static/assets/index-BNL1GQD1.css
app/static/assets/index-BNsTrZn7.js
app/static/assets/index-BOjJDTjf.js
app/static/assets/index-BOn6lsTC.css
app/static/assets/index-BYP2NuHo.js
app/static/assets/index-BYpSyUuE.css
app/static/assets/index-BZuvixxW.css
app/static/assets/index-Bc21j6Jb.js
app/static/assets/index-BfCuSiTx.css
owlapp-0.3.23.dist-info/METADATA
owlapp-0.3.23.dist-info/WHEEL
owlapp-0.3.23.dist-info/entry_points.txt
owlapp-0.3.23.dist-info/RECORD
