Metadata-Version: 2.1
Name: owlapp
Version: 0.3.23
Summary: 
Author: Ceyhun Kerti
Author-email: ceyhun.kerti@gmail.com
Requires-Python: >=3.12,<4.0
Classifier: Programming Language :: Python :: 3
Classifier: Programming Language :: Python :: 3.12
Requires-Dist: alembic (>=1.13.1)
Requires-Dist: apiflask (>=2.2.1,<3.0.0)
Requires-Dist: authlib (>=1.3.1)
Requires-Dist: click (>=8.1.7)
Requires-Dist: duckdb (>=1.0.0)
Requires-Dist: flask (>=3.0.3)
Requires-Dist: flask-compress (>=1.15)
Requires-Dist: flask-cors (>=4.0.1)
Requires-Dist: flask-jwt-extended[asymmetric-crypto] (>=4.6.0)
Requires-Dist: flask-migrate (>=4.0.7)
Requires-Dist: flask-sqlalchemy (>=3.1.1)
Requires-Dist: gunicorn (>=22.0.0)
Requires-Dist: jinja2 (>=3.1.4,<4.0.0)
Requires-Dist: marshmallow-dataclass (>=8.7.0,<9.0.0)
Requires-Dist: polars (>=1.2.1)
Requires-Dist: psycopg2-binary (>=2.9.9)
Requires-Dist: ptpython (>=3.0.27)
Requires-Dist: pyarrow (>=17.0.0,<18.0.0)
Requires-Dist: pydantic-settings (>=2.3.1)
Requires-Dist: pydantic[email] (>=2.8.2)
Requires-Dist: pydash (>=8.0.1)
Requires-Dist: pynacl (>=1.5.0)
Requires-Dist: pyopenssl (>=24.1.0)
Requires-Dist: pytest (>=8.2.2)
Requires-Dist: requests (>=2.32.3)
Requires-Dist: rich (>=13.7.1)
Requires-Dist: ruff (>=0.5.5)
Requires-Dist: sqlparse (>=0.5.1)
